libfoot-0.0.1.dist-info/METADATA
libfoot-0.0.1.dist-info/WHEEL
libfoot-0.0.1.dist-info/entry_points.txt
libfoot-0.0.1.dist-info/licenses/LICENSE
libfoot/types.py
libfoot/display.py
libfoot/py.typed
libfoot/__init__.py
libfoot/cli.py
libfoot/_libfoot.pyi
libfoot/_libfoot.pypy310-pp73-x86-linux-gnu.so
libfoot-0.0.1.dist-info/RECORD
